pyaocs/parameters.py
pyaocs/utils.py
pyaocs/control/example.py
pyaocs/simulation/__init__.py
pyaocs/simulation/actuator.py
pyaocs/simulation/digital_twin.py
pyaocs/simulation/disturbances.py
pyaocs/simulation/environment.py
pyaocs/simulation/noise.py
pyaocs/simulation/non_linear_equations.py
pyaocs/urdf_models/cylinder.urdf
pyaocs-0.0.5.dist-info/METADATA
pyaocs-0.0.5.dist-info/WHEEL
pyaocs-0.0.5.dist-info/licenses/LICENSE
pyaocs-0.0.5.dist-info/RECORD
