Metadata-Version: 2.3
Name: pyaocs
Version: 0.0.5
Summary: Satellite Digital Twin to test control strategies.
Project-URL: Homepage, https://github.com/pr1u20/AOCS-digital-twin
Project-URL: Bug Tracker, https://github.com/pr1u20/AOCS-digital-twin/issues
Author-email: Pedro <pr1u20@soton.ac.uk>
License: MIT License
License-File: LICENSE
Classifier: License :: OSI Approved :: MIT License
Classifier: Operating System :: OS Independent
Classifier: Programming Language :: Python :: 3
Requires-Python: >=3.9
Requires-Dist: matplotlib
Requires-Dist: numpy
Requires-Dist: pybullet
